gcloud_functions_params/__init__.py
gcloud_functions_params-0.0.2.dist-info/DESCRIPTION.rst
gcloud_functions_params-0.0.2.dist-info/METADATA
gcloud_functions_params-0.0.2.dist-info/RECORD
gcloud_functions_params-0.0.2.dist-info/WHEEL
gcloud_functions_params-0.0.2.dist-info/metadata.json
gcloud_functions_params-0.0.2.dist-info/top_level.txt
